jsondatetime/__init__.py
jsondatetime/jsondatetime.py
jsondatetime/tests/__init__.py
jsondatetime/tests/test_jsondatetime.py
sts_json_datetime-0.0.10.dist-info/LICENSE
sts_json_datetime-0.0.10.dist-info/METADATA
sts_json_datetime-0.0.10.dist-info/WHEEL
sts_json_datetime-0.0.10.dist-info/top_level.txt
sts_json_datetime-0.0.10.dist-info/RECORD
