Metadata-Version: 2.1
Name: sts-json-datetime
Version: 0.0.10
Summary: Allows for proper decoding of datetime values contained in JSON streams
Home-page: https://github.com/tbindseil/sts-mono-repo
Author: TJ Bindseil
Author-email: tjbindseil@gmail.com
License: ISC
Platform: any
Classifier: Programming Language :: Python :: 3
Classifier: License :: OSI Approved :: MIT License
Classifier: Operating System :: OS Independent
